repo_helper_pycharm-0.3.0.dist-info/WHEEL
repo_helper_pycharm-0.3.0.dist-info/entry_points.txt
repo_helper_pycharm-0.3.0.dist-info/METADATA
repo_helper_pycharm-0.3.0.dist-info/top_level.txt
repo_helper_pycharm-0.3.0.dist-info/LICENSE
repo_helper_pycharm/register_schema.py
repo_helper_pycharm/docs.py
repo_helper_pycharm/py.typed
repo_helper_pycharm/iml_manager.py
repo_helper_pycharm/__init__.py
repo_helper_pycharm-0.3.0.dist-info/RECORD
