Metadata-Version: 2.1
Name: repo-helper-pycharm
Version: 0.3.0
Summary: repo_helper extension to manage PyCharm's configuration.
Author-email: Dominic Davis-Foster <dominic@davis-foster.co.uk>
License: MIT
Keywords: pycharm,repo-helper
Home-page: https://github.com/repo-helper/repo_helper_pycharm
Project-URL: Issue Tracker, https://github.com/repo-helper/repo_helper_pycharm/issues
Project-URL: Source Code, https://github.com/repo-helper/repo_helper_pycharm
Project-URL: Documentation, https://repo_helper_pycharm.readthedocs.io/en/latest
Platform: Windows
Platform: macOS
Platform: Linux
Classifier: Development Status :: 4 - Beta
Classifier: Environment :: Console
Classifier: Intended Audience :: Developers
Classifier: License :: OSI Approved :: MIT License
Classifier: Operating System :: OS Independent
Classifier: Programming Language :: Python
Classifier: Programming Language :: Python :: 3 :: Only
Classifier: Programming Language :: Python :: 3.6
Classifier: Programming Language :: Python :: 3.7
Classifier: Programming Language :: Python :: 3.8
Classifier: Programming Language :: Python :: 3.9
Classifier: Programming Language :: Python :: Implementation :: CPython
Classifier: Typing :: Typed
Requires-Python: >=3.6
Requires-Dist: apeye>=0.4.1
Requires-Dist: appdirs>=1.4.4
Requires-Dist: click>=7.1.2
Requires-Dist: consolekit>=1.0.0
Requires-Dist: domdf-python-tools>=2.4.0
Requires-Dist: lxml>=4.6.1
Requires-Dist: repo-helper>=2020.12.8
